photon_mosaic/__init__.py
photon_mosaic/cli.py
photon_mosaic/dataset_discovery.py
photon_mosaic/pathing.py
photon_mosaic/preprocessing/__init__.py
photon_mosaic/preprocessing/contrast.py
photon_mosaic/preprocessing/derotation.py
photon_mosaic/preprocessing/noop.py
photon_mosaic/rules/__init__.py
photon_mosaic/rules/preprocessing.py
photon_mosaic/rules/suite2p_run.py
photon_mosaic/workflow/Snakefile
photon_mosaic/workflow/config.yaml
photon_mosaic/workflow/preprocessing.smk
photon_mosaic/workflow/suite2p.smk
photon_mosaic-0.2.1.dist-info/licenses/LICENCE
photon_mosaic-0.2.1.dist-info/METADATA
photon_mosaic-0.2.1.dist-info/WHEEL
photon_mosaic-0.2.1.dist-info/entry_points.txt
photon_mosaic-0.2.1.dist-info/top_level.txt
photon_mosaic-0.2.1.dist-info/RECORD
