Metadata-Version: 2.4
Name: photon-mosaic
Version: 0.2.1
Summary: Automating calcium imaging analysis
Author-email: Laura Porta <ucqflpo@ucl.ac.uk>
License: BSD-3-Clause
Project-URL: Homepage, https://github.com/neuroinformatics-unit/photon-mosaic
Project-URL: Bug Tracker, https://github.com/neuroinformatics-unit/photon-mosaic/issues
Project-URL: Documentation, https://photon-mosaic.neuroinformatics.dev
Project-URL: Source Code, https://github.com/neuroinformatics-unit/photon-mosaic
Project-URL: User Support, https://github.com/neuroinformatics-unit/photon-mosaic/issues
Classifier: Development Status :: 2 - Pre-Alpha
Classifier: Programming Language :: Python
Classifier: Programming Language :: Python :: 3
Classifier: Programming Language :: Python :: 3.11
Classifier: Programming Language :: Python :: 3.12
Classifier: Operating System :: OS Independent
Classifier: License :: OSI Approved :: BSD License
Requires-Python: >=3.11.0
License-File: LICENCE
Requires-Dist: snakemake
Requires-Dist: numpy
Requires-Dist: snakemake-executor-plugin-slurm
Requires-Dist: PyYAML
Requires-Dist: derotation
Requires-Dist: suite2p-NIU
Provides-Extra: dev
Requires-Dist: pytest; extra == "dev"
Requires-Dist: pytest-cov; extra == "dev"
Requires-Dist: coverage; extra == "dev"
Requires-Dist: tox; extra == "dev"
Requires-Dist: mypy; extra == "dev"
Requires-Dist: pre-commit; extra == "dev"
Requires-Dist: ruff; extra == "dev"
Requires-Dist: setuptools_scm; extra == "dev"
Dynamic: license-file
